{
  "session_id": "int_415470107_a1b97b38",
  "state": "COMPLETED",
  "mode": "STANDARD",
  "iteration_count": 0,
  "repair_attempts": 0,
  "material_type": "unknown",
  "completeness": "unknown",
  "accumulated_material": [
    {
      "timestamp": "2026-02-06T13:33:37.969717+00:00",
      "content": "Мне приснился сон: я нахожусь в своём детском доме, но он какой-то другой, не такой как раньше. Там есть дверь, которая заперта, и я не могу найти ключ. Я чувствую сильное желание открыть эту дверь, но не получается. В доме есть другие люди, но они далеко и не отвечают, когда я их зову."
    },
    {
      "timestamp": "2026-02-06T13:34:00.231296+00:00",
      "content": "Единственный"
    },
    {
      "timestamp": "2026-02-06T13:34:25.673654+00:00",
      "content": "Сноведение, которое я предоставил"
    },
    {
      "timestamp": "2026-02-06T13:34:38.293082+00:00",
      "content": "Мне приснился сон: я нахожусь в своём детском доме, но он какой-то другой, не такой как раньше. Там есть дверь, которая заперта, и я не могу найти ключ. Я чувствую сильное желание открыть эту дверь, но не получается. В доме есть другие люди, но они далеко и не отвечают, когда я их зову."
    },
    {
      "timestamp": "2026-02-06T13:34:52.446039+00:00",
      "content": "Да"
    }
  ],
  "clarifications_received": [],
  "created_at": "2026-02-06T13:33:23.723324+00:00",
  "updated_at": "2026-02-06T13:35:21.772689+00:00"
}